{
  "type": "minecraft:block",
  "pools": [
    {
      "bonus_rolls": 0.0,
      "conditions": [
        {
          "condition": "minecraft:inverted",
          "term": {
            "block": "sinofoundation:cabbage_plant",
            "condition": "minecraft:block_state_property",
            "properties": {
              "age": "3"
            }
          }
        }
      ],
      "entries": [
        {
          "type": "minecraft:item",
          "functions": [
            {
              "add": false,
              "count": {
                "type": "minecraft:uniform",
                "max": 1.0,
                "min": 1.0
              },
              "function": "minecraft:set_count"
            }
          ],
          "name": "sinofoundation:cabbage_seed"
        }
      ],
      "rolls": 1.0
    },
    {
      "bonus_rolls": 0.0,
      "conditions": [
        {
          "block": "sinofoundation:cabbage_plant",
          "condition": "minecraft:block_state_property",
          "properties": {
            "age": "3"
          }
        }
      ],
      "entries": [
        {
          "type": "minecraft:item",
          "functions": [
            {
              "add": false,
              "count": {
                "type": "minecraft:uniform",
                "max": 5.0,
                "min": 2.0
              },
              "function": "minecraft:set_count"
            }
          ],
          "name": "sinofoundation:cabbage"
        }
      ],
      "rolls": 1.0
    }
  ],
  "random_sequence": "sinofoundation:blocks/cabbage_plant"
}